{
  "agra-fort": "Agra Fort red sandstone walls with Yamuna river, Uttar Pradesh",
  "amber-fort-jaipur": "Amber Fort Jaipur on Aravalli hills, elephant ascending ramp, Rajasthan",
  "amritsar-golden-temple": "Golden Temple Amritsar reflecting on sarovar at dusk, devotees, Punjab",
  "ayodhya-ram-mandir": "Ayodhya Ram Mandir grand temple at sunset, devotees, Uttar Pradesh",
  "badrinath-temple": "Badrinath Temple colorful facade with Neelkanth peak in Garhwal Himalayas",
  "chandigarh-rose-garden": "Chandigarh tree-lined avenue with car driving towards hills, Punjab",
  "delhi-india-gate": "India Gate Delhi war memorial at sunset with vehicles passing",
  "delhi-red-fort": "Delhi Red Fort sandstone gate with Indian flag, Old Delhi",
  "dhanaulti-eco-park": "Dhanaulti eco park pine forest hills, Uttarakhand",
  "gangotri-source-ganges": "Gangotri Temple Garhwal Himalayas at the source of Ganges, snow peaks",
  "garhwal-pilgrim-town": "Garhwal Himalayan pilgrim town with hilltop temple, Uttarakhand",
  "haridwar-har-ki-pauri": "Haridwar Har ki Pauri ghat at evening Ganga aarti with floating diyas",
  "jaipur-hawa-mahal": "Hawa Mahal Jaipur pink palace facade at golden hour, Rajasthan Pink City",
  "jaipur-pink-city": "Jaipur Pink City rooftop view with Hawa Mahal and bazaar, Rajasthan",
  "jaisalmer-fort-golden": "Jaisalmer Golden Fort sandstone walls glowing at sunset, Thar Desert",
  "jhansi-orchha": "Orchha Raja Mahal palace ruins with Betwa river, Madhya Pradesh border",
  "jim-corbett-safari": "Jim Corbett tiger reserve safari jeep with elephant grass, Uttarakhand",
  "jodhpur-mehrangarh": "Mehrangarh Fort Jodhpur looming above blue houses of old town, Rajasthan",
  "kashmir-betaab-valley": "Betaab Valley meadow surrounded by deodar pines, Kashmir, summer green",
  "kashmir-gulmarg-meadow": "Gulmarg snow meadow with pine trees and Himalayan peaks, Kashmir, winter morning",
  "kashmir-gurez-valley": "Remote Gurez Valley with Habba Khatoon peak and Kishanganga river, Kashmir",
  "kashmir-mughal-gardens": "Mughal Gardens of Kashmir with terraced lawns and tulips, Dal Lake view, Srinagar",
  "kashmir-pahalgam-lidder": "Pahalgam valley with Lidder river flowing through pine forest, Kashmir",
  "kashmir-shikara-dal-lake": "Traditional shikara wooden boat on Dal Lake at golden hour, snow-capped mountains in background, Srinagar Kashmir",
  "kashmir-sonmarg-glacier": "Sonmarg Thajiwas glacier with snow-capped mountains, alpine meadow, Kashmir",
  "khajjiar-meadow": "Khajjiar meadow Himachal called Mini Switzerland with cedar forest",
  "manali-old-town": "Old Manali wooden architecture with Beas river and pine forest, Himachal",
  "manali-valley": "Manali valley with snow peaks, Beas river and apple orchards, Himachal",
  "mathura-vrindavan": "Vrindavan Banke Bihari temple with colorful holi powders, Uttar Pradesh",
  "mcleodganj-monastery": "McLeodganj Tibetan monastery with prayer wheels, Dharamshala Himachal",
  "mount-abu-nakki-lake": "Mount Abu Nakki Lake at dusk with hill station town, Rajasthan",
  "mussoorie-mall-road": "Mussoorie Mall Road queen of hills with mountain views, Uttarakhand",
  "nainital-naini-lake": "Nainital Naini Lake with town reflecting on water, hill station Uttarakhand",
  "prayagraj-sangam": "Prayagraj Triveni Sangam confluence of Ganga Yamuna Saraswati, boats",
  "pushkar-lake-ghats": "Pushkar holy lake with white temples and ghats, Brahma temple, Rajasthan",
  "ranikhet-chaubatia-orchard": "Ranikhet Chaubatia apple orchard with view of Himalayas, Uttarakhand",
  "ranthambore-tiger-safari": "Ranthambore tiger walking through dry grass with safari jeep, Rajasthan",
  "rishikesh-rafting": "Rishikesh white water rafting on Ganges with mountains, Uttarakhand",
  "shimla-mall-road": "Shimla Mall Road with colonial Christ Church and pedestrians, Himachal",
  "shimla-ridge-himachal": "Shimla ridge with Christ Church and town view, Himachal",
  "solang-valley-snow": "Solang Valley Himachal with snow paragliding, Rohtang Pass mountains",
  "spiti-kaza-village": "Spiti Valley Kaza village in cold desert, whitewashed houses, Himachal",
  "vaishno-devi-katra": "Trikuta hills with Vaishno Devi pilgrimage path, Katra Jammu, devotees walking",
  "varanasi-ganga-aarti": "Varanasi Dashashwamedh ghat Ganga aarti at dusk, priests with brass lamps",
  "yamunotri-shrine": "Yamunotri shrine in Garhwal Himalayas with surya kund hot springs, pilgrims"
}